django_zxcvbn_password_validator/__init__.py
django_zxcvbn_password_validator/settings.py
django_zxcvbn_password_validator/test_translate_zxcvbn_text.py
django_zxcvbn_password_validator/test_zxcvbn_password_validator.py
django_zxcvbn_password_validator/translate_zxcvbn_text.py
django_zxcvbn_password_validator/zxcvbn_password_validator.py
django_zxcvbn_password_validator/locale/ar/LC_MESSAGES/django.mo
django_zxcvbn_password_validator/locale/ar/LC_MESSAGES/django.po
django_zxcvbn_password_validator/locale/cs/LC_MESSAGES/django.mo
django_zxcvbn_password_validator/locale/cs/LC_MESSAGES/django.po
django_zxcvbn_password_validator/locale/de/LC_MESSAGES/django.mo
django_zxcvbn_password_validator/locale/de/LC_MESSAGES/django.po
django_zxcvbn_password_validator/locale/es/LC_MESSAGES/django.mo
django_zxcvbn_password_validator/locale/es/LC_MESSAGES/django.po
django_zxcvbn_password_validator/locale/fr/LC_MESSAGES/django.mo
django_zxcvbn_password_validator/locale/fr/LC_MESSAGES/django.po
django_zxcvbn_password_validator/locale/ha/LC_MESSAGES/django.mo
django_zxcvbn_password_validator/locale/ha/LC_MESSAGES/django.po
django_zxcvbn_password_validator/locale/hi/LC_MESSAGES/django.mo
django_zxcvbn_password_validator/locale/hi/LC_MESSAGES/django.po
django_zxcvbn_password_validator/locale/hu/LC_MESSAGES/django.mo
django_zxcvbn_password_validator/locale/hu/LC_MESSAGES/django.po
django_zxcvbn_password_validator/locale/hy/LC_MESSAGES/django.mo
django_zxcvbn_password_validator/locale/hy/LC_MESSAGES/django.po
django_zxcvbn_password_validator/locale/id/LC_MESSAGES/django.mo
django_zxcvbn_password_validator/locale/id/LC_MESSAGES/django.po
django_zxcvbn_password_validator/locale/it/LC_MESSAGES/django.mo
django_zxcvbn_password_validator/locale/it/LC_MESSAGES/django.po
django_zxcvbn_password_validator/locale/ja/LC_MESSAGES/django.mo
django_zxcvbn_password_validator/locale/ja/LC_MESSAGES/django.po
django_zxcvbn_password_validator/locale/ko/LC_MESSAGES/django.mo
django_zxcvbn_password_validator-1.5.3.dist-info/licenses/LICENSE
django_zxcvbn_password_validator-1.5.3.dist-info/METADATA
django_zxcvbn_password_validator-1.5.3.dist-info/WHEEL
django_zxcvbn_password_validator-1.5.3.dist-info/top_level.txt
django_zxcvbn_password_validator-1.5.3.dist-info/RECORD
