Metadata-Version: 2.4
Name: django-zxcvbn-password-validator
Version: 1.5.3
Summary: A translatable password validator for django, based on zxcvbn-python.
Author-email: Pierre SASSOULAS <pierre.sassoulas@gmail.com>
License-Expression: MIT
Project-URL: Bug Tracker, https://github.com/Pierre-Sassoulas/django-zxcvbn-password-validator/issues
Project-URL: Source Code, https://github.com/Pierre-Sassoulas/django-zxcvbn-password-validator
Keywords: django,password-validator,zxcvbn
Classifier: Development Status :: 5 - Production/Stable
Classifier: Framework :: Django
Classifier: Framework :: Django :: 3.2
Classifier: Framework :: Django :: 4.2
Classifier: Framework :: Django :: 5.2
Classifier: Framework :: Django :: 6.0
Classifier: Intended Audience :: Developers
Classifier: Natural Language :: Arabic
Classifier: Natural Language :: Armenian
Classifier: Natural Language :: Chinese (Simplified)
Classifier: Natural Language :: Czech
Classifier: Natural Language :: Dutch
Classifier: Natural Language :: English
Classifier: Natural Language :: French
Classifier: Natural Language :: German
Classifier: Natural Language :: Hindi
Classifier: Natural Language :: Hungarian
Classifier: Natural Language :: Indonesian
Classifier: Natural Language :: Italian
Classifier: Natural Language :: Japanese
Classifier: Natural Language :: Korean
Classifier: Natural Language :: Polish
Classifier: Natural Language :: Portuguese
Classifier: Natural Language :: Portuguese (Brazilian)
Classifier: Natural Language :: Russian
Classifier: Natural Language :: Spanish
Classifier: Natural Language :: Thai
Classifier: Natural Language :: Turkish
Classifier: Natural Language :: Ukrainian
Classifier: Natural Language :: Vietnamese
Classifier: Operating System :: OS Independent
Classifier: Programming Language :: Python :: 3 :: Only
Classifier: Programming Language :: Python :: 3.10
Classifier: Programming Language :: Python :: 3.11
Classifier: Programming Language :: Python :: 3.12
Classifier: Programming Language :: Python :: 3.13
Classifier: Programming Language :: Python :: 3.14
Requires-Python: >=3.10
License-File: LICENSE
Requires-Dist: django<7,>=2
Requires-Dist: zxcvbn
Provides-Extra: dev
Requires-Dist: build; extra == "dev"
Requires-Dist: coverage; extra == "dev"
Requires-Dist: coveralls; extra == "dev"
Requires-Dist: django-rosetta; extra == "dev"
Requires-Dist: mock; extra == "dev"
Requires-Dist: pre-commit; extra == "dev"
Requires-Dist: python-coveralls; extra == "dev"
Provides-Extra: pylint
Requires-Dist: pre-commit>=2.16; extra == "pylint"
Requires-Dist: pylint>=3.2; extra == "pylint"
Requires-Dist: pylint-django==2.7; extra == "pylint"
Dynamic: license-file
